hellodipesh/__init__.py
hellodipesh/counter.py
my_pyspark_package-0.1.0.dist-info/METADATA
my_pyspark_package-0.1.0.dist-info/WHEEL
my_pyspark_package-0.1.0.dist-info/top_level.txt
my_pyspark_package-0.1.0.dist-info/RECORD
